<annotation>
	<folder>images</folder>
	<filename>IMG_5149.jpg</filename>
	<path>/Users/areej/Desktop/apparel/images/IMG_5149.jpg</path>
	<source>
		<database>Unknown</database>
	</source>
	<size>
		<width>2304</width>
		<height>2305</height>
		<depth>3</depth>
	</size>
	<segmented>0</segmented>
	<object>
		<name>shoes</name>
		<pose>Unspecified</pose>
		<truncated>0</truncated>
		<difficult>0</difficult>
		<bndbox>
			<xmin>205</xmin>
			<ymin>48</ymin>
			<xmax>1235</xmax>
			<ymax>1483</ymax>
		</bndbox>
	</object>
	<object>
		<name>shoes</name>
		<pose>Unspecified</pose>
		<truncated>0</truncated>
		<difficult>0</difficult>
		<bndbox>
			<xmin>1024</xmin>
			<ymin>696</ymin>
			<xmax>1878</xmax>
			<ymax>2258</ymax>
		</bndbox>
	</object>
</annotation>
